Metadata-Version: 2.1
Name: django-password-validator
Version: 0.2.0
Summary: django-password-validator is a reusable app that provides a form field and validators that check the strength of a password.
License: LICENSE
Keywords: password,validator
Author: Dharwin Perez
Author-email: dharwin@codelovers.club
Requires-Python: >=3.10,<4.0
Classifier: License :: Other/Proprietary License
Classifier: Programming Language :: Python :: 3
Classifier: Programming Language :: Python :: 3.10
Classifier: Programming Language :: Python :: 3.11
Classifier: Programming Language :: Python :: 3.12
Requires-Dist: django (>=4.0,<5.0)
